<?xml version="1.0" encoding="UTF-8" standalone="yes"?>
<root>
  <name>陈和平</name>
  <resume>重庆市政府网www.cq.gov.cn2012年08月07日12时44分市政府办公厅
陈和平，男，汉族，1956年4月生，江西清江人，大学，经济学学士，经济师，1974年7月参加工作，1985年7月加入中国共产党。现任重庆市政府副市长、党组成员。
1974.07—1975.09四川省奉节县双潭公社知青
1975.09—1979.09长航重庆航道区奉节航道段工人
1979.09—1983.07北京商学院商业经济系商业经济专业学习，获经济学学士学位
1983.07—1984.07四川省万县地区糖酒公司干部
1984.07—1986.02四川省万县地区商业局秘书、办公室副主任、主任
1986.02—1991.07四川省万县地区商业局副局长
1991.07—1993.03四川省万县地区商业局局长，1992.06党委书记
1993.03—1994.03四川省万县地区行政公署党组成员、副秘书长，办公厅主任
1994.03—1997.07四川省万县市政府秘书长、党组成员，办公厅主任、党组书记
1997.07—2000.05重庆市委组织部秘书长
2000.05—2004.04重庆市委组织部副部长，2003.02正厅局级
2004.04—2012.08重庆市政府党组成员，办公厅主任、党组书记，2004.05市政府秘书长，2008.12市政府参事室主任
2012.08—2012.10重庆市政府副市长、党组成员，市政府秘书长、办公厅主任、党组书记，市政府参事室主任
2012.10—2012.11重庆市政府副市长、党组成员，市政府秘书长
2012.11—2016.06重庆市政府副市长、党组成员2016.06—重庆市政府党组成员
党的十七大、十八大代表，市三次、四次党代会代表，三届、四届市委委员，市四届人大代表负责市交通规划建设领导小组工作。
【大中小】【置顶】【打印】【关闭窗口】
</resume>
  <url>http://www.cq.gov.cn/zwgk/zfld/szfld/vicemayor/54171.shtml</url>
  <org>重庆</org>
  <href>陈和平</href>
</root>