<?xml version="1.0" encoding="UTF-8" standalone="yes"?>
<root>
  <name>梁桂常务副省长党组副书记</name>
  <resume>梁桂常务副省长党组副书记
梁桂，男，1964年8月生，汉族，安徽合肥人，1984年7月参加工作，1993年6月加入中国共产党，全日制博士研究生，理学博士，研究员。历任上海市浦东新区综合规划土地局副处级干部、浦东新区党工委（管委会）政策研究室副主任（正处级）、浦东生产力促进中心主任、浦东新区经济贸易局副局长，浦东新区科学技术局局长、党组书记兼浦东新区科协副主席，国家科技部火炬高技术产业开发中心副主任、主任兼科技型中小企业创新基金管理中心主任，杨凌农业高新技术产业示范区党工委书记、西北农林科技大学党委副书记，2013年5月任西北农林科技大学党委书记（副部长级），2015年7月任陕西省委常委，2015年8月任陕西省委常委、宣传部部长，2016年12月任陕西省委常委、宣传部部长，省政府副省长、党组副书记。中共十八大代表，省第十二次党代会代表，省十二届人大代表。
负责省政府常务工作和发展改革、人力资源和社会保障、编制、金融、监察、税务、电力、政务公开以及关天规划实施和西咸新区、陕北能源化工基地建设、陕南循环发展方面的工作。分管省政府办公厅（金融办）、省发展改革委（粮食局）、省监察厅、省人力资源社会保障厅（公务员局）、省编办、省地税局、省统计局、省机关事务管理局、西咸新区管委会。协助分管财政工作。联系驻陕部队、省国税局、国家统计局陕西调查总队、西安铁路局、省决策咨询委、金融机构驻陕单位、国家能源局西北监管局、西北电网公司、省电力公司、大唐陕西发电公司、华电陕西能源公司、华能陕西发电公司、国电西北分公司、国家电投陕西分公司、陕西能源集团、陕西地方电力集团、陕西金融控股集团、陕西海外投资公司、永安保险公司、陕国投、长安银行、秦农银行、省农信联社、陕西金融资产管理公司、香港骊山公司。协助联系财政部专员办。
邮件服务|RTX服务|意见建议|违法和不良信息举报
省政府办公厅主管省电子政务办公室承办陕ICP备10004160号
技术支持：陕西时光软件有限公司
</resume>
  <url>http://www.shaanxi.gov.cn/info/iIndex.jsp?cat_id=10011</url>
  <org>陕西</org>
  <href/>
</root>